debpackager/__init__.py
debpackager/main.py
debpackager/conf/__init__.py
debpackager/conf/configuratoin.py
debpackager/conf/log_conf.py
debpackager/packages/__init__.py
debpackager/packages/general_package.py
debpackager/packages/conf/__init__.py
debpackager/packages/conf/configurations.py
debpackager/packages/general/__init__.py
debpackager/packages/general/general.py
debpackager/packages/python/__init__.py
debpackager/packages/python/python.py
debpackager/utils/__init__.py
debpackager/utils/debain_package_manager.py
debpackager/utils/general.py
debpackager/utils/pom.py
debpackager-0.2.1.dist-info/DESCRIPTION.rst
debpackager-0.2.1.dist-info/METADATA
debpackager-0.2.1.dist-info/RECORD
debpackager-0.2.1.dist-info/WHEEL
debpackager-0.2.1.dist-info/entry_points.txt
debpackager-0.2.1.dist-info/metadata.json
debpackager-0.2.1.dist-info/top_level.txt
