Metadata-Version: 2.0
Name: debpackager
Version: 0.2.1
Summary: debpackager package any project to debian package
Home-page: https://github.com/urban48/debpackager
Author: Sergey R.
Author-email: segrog@gmail.com
License: MIT
Keywords: debian deb packaging package daemon dh-make
Platform: UNKNOWN
Classifier: Development Status :: 3 - Alpha
Classifier: Intended Audience :: Developers
Classifier: Topic :: Software Development :: Build Tools
Classifier: License :: OSI Approved :: MIT License
Classifier: Programming Language :: Python :: 2
Classifier: Programming Language :: Python :: 2.7
Classifier: Programming Language :: Python :: 3
Classifier: Programming Language :: Python :: 3.4
Classifier: Programming Language :: Python :: 3.5
Requires-Dist: sh (==1.11)
Requires-Dist: semantic-version (==2.5.0)
Requires-Dist: virtualenv (==15.0.2)
Requires-Dist: pytest-runner (==2.8)
